<?xml version="1.0" encoding="ISO-8859-1" standalone="yes"?>
<nite:root nite:id="ES2016c.C.dialog-act" xmlns:nite="http://nite.sourceforge.net/">
   <dact nite:id="ES2016c.C.dialog-act.dharshi.1">
      <nite:pointer role="da-aspect"  href="da-types.xml#id(ami_da_4)"/>
      <nite:child href="ES2016c.C.words.xml#id(ES2016c.C.words0)..id(ES2016c.C.words1)"/>
   </dact>
   <dact nite:id="ES2016c.C.dialog-act.dharshi.2">
      <nite:pointer role="da-aspect"  href="da-types.xml#id(ami_da_6)"/>
      <nite:child href="ES2016c.C.words.xml#id(ES2016c.C.words2)..id(ES2016c.C.words10)"/>
   </dact>
   <dact nite:id="ES2016c.C.dialog-act.dharshi.4">
      <nite:pointer role="da-aspect"  href="da-types.xml#id(ami_da_4)"/>
      <nite:child href="ES2016c.C.words.xml#id(ES2016c.C.words11)..id(ES2016c.C.words20)"/>
   </dact>
   <dact nite:id="ES2016c.C.dialog-act.dharshi.3">
      <nite:pointer role="da-aspect"  href="da-types.xml#id(ami_da_3)"/>
      <nite:child href="ES2016c.C.words.xml#id(ES2016c.C.words21)"/>
   </dact>
   <dact nite:id="ES2016c.C.dialog-act.dharshi.5">
      <nite:pointer role="da-aspect"  href="da-types.xml#id(ami_da_5)"/>
      <nite:child href="ES2016c.C.words.xml#id(ES2016c.C.words22)..id(ES2016c.C.words25)"/>
   </dact>
   <dact nite:id="ES2016c.C.dialog-act.dharshi.6">
      <nite:pointer role="da-aspect"  href="da-types.xml#id(ami_da_3)"/>
      <nite:child href="ES2016c.C.words.xml#id(ES2016c.C.words26)..id(ES2016c.C.words29)"/>
   </dact>
   <dact nite:id="ES2016c.C.dialog-act.dharshi.9">
      <nite:pointer role="da-aspect"  href="da-types.xml#id(ami_da_9)"/>
      <nite:child href="ES2016c.C.words.xml#id(ES2016c.C.words30)..id(ES2016c.C.words33)"/>
   </dact>
   <dact nite:id="ES2016c.C.dialog-act.dharshi.10">
      <nite:pointer role="da-aspect"  href="da-types.xml#id(ami_da_9)"/>
      <nite:child href="ES2016c.C.words.xml#id(ES2016c.C.words34)..id(ES2016c.C.words36)"/>
   </dact>
   <dact nite:id="ES2016c.C.dialog-act.dharshi.11">
      <nite:pointer role="da-aspect"  href="da-types.xml#id(ami_da_2)"/>
      <nite:child href="ES2016c.C.words.xml#id(ES2016c.C.words37)..id(ES2016c.C.words38)"/>
   </dact>
   <dact nite:id="ES2016c.C.dialog-act.dharshi.12">
      <nite:pointer role="da-aspect"  href="da-types.xml#id(ami_da_3)"/>
      <nite:child href="ES2016c.C.words.xml#id(ES2016c.C.words39)..id(ES2016c.C.words44)"/>
   </dact>
   <dact nite:id="ES2016c.C.dialog-act.dharshi.13">
      <nite:pointer role="da-aspect"  href="da-types.xml#id(ami_da_9)"/>
      <nite:child href="ES2016c.C.words.xml#id(ES2016c.C.words45)..id(ES2016c.C.words46)"/>
   </dact>
   <dact nite:id="ES2016c.C.dialog-act.dharshi.14" reflexivity="true">
      <nite:pointer role="da-aspect"  href="da-types.xml#id(ami_da_7)"/>
      <nite:child href="ES2016c.C.words.xml#id(ES2016c.C.words47)..id(ES2016c.C.words73)"/>
   </dact>
   <dact nite:id="ES2016c.C.dialog-act.dharshi.15">
      <nite:pointer role="da-aspect"  href="da-types.xml#id(ami_da_4)"/>
      <nite:child href="ES2016c.C.words.xml#id(ES2016c.C.words74)..id(ES2016c.C.words94)"/>
   </dact>
   <dact nite:id="ES2016c.C.dialog-act.dharshi.16">
      <nite:pointer role="da-aspect"  href="da-types.xml#id(ami_da_4)"/>
      <nite:child href="ES2016c.C.words.xml#id(ES2016c.C.words95)..id(ES2016c.C.words106)"/>
   </dact>
   <dact nite:id="ES2016c.C.dialog-act.dharshi.17">
      <nite:pointer role="da-aspect"  href="da-types.xml#id(ami_da_4)"/>
      <nite:child href="ES2016c.C.words.xml#id(ES2016c.C.words107)..id(ES2016c.C.words139)"/>
   </dact>
   <dact nite:id="ES2016c.C.dialog-act.dharshi.18">
      <nite:pointer role="da-aspect"  href="da-types.xml#id(ami_da_4)"/>
      <nite:child href="ES2016c.C.words.xml#id(ES2016c.C.words140)..id(ES2016c.C.words164)"/>
   </dact>
   <dact nite:id="ES2016c.C.dialog-act.dharshi.19">
      <nite:pointer role="da-aspect"  href="da-types.xml#id(ami_da_2)"/>
      <nite:child href="ES2016c.C.words.xml#id(ES2016c.C.words165)..id(ES2016c.C.words167)"/>
   </dact>
   <dact nite:id="ES2016c.C.dialog-act.dharshi.20">
      <nite:pointer role="da-aspect"  href="da-types.xml#id(ami_da_4)"/>
      <nite:child href="ES2016c.C.words.xml#id(ES2016c.C.words168)..id(ES2016c.C.words181)"/>
   </dact>
   <dact nite:id="ES2016c.C.dialog-act.dharshi.21">
      <nite:pointer role="da-aspect"  href="da-types.xml#id(ami_da_4)"/>
      <nite:child href="ES2016c.C.words.xml#id(ES2016c.C.words182)..id(ES2016c.C.words199)"/>
   </dact>
   <dact nite:id="ES2016c.C.dialog-act.dharshi.22">
      <nite:pointer role="da-aspect"  href="da-types.xml#id(ami_da_4)"/>
      <nite:child href="ES2016c.C.words.xml#id(ES2016c.C.words200)..id(ES2016c.C.words215)"/>
   </dact>
   <dact nite:id="ES2016c.C.dialog-act.dharshi.23">
      <nite:pointer role="da-aspect"  href="da-types.xml#id(ami_da_4)"/>
      <nite:child href="ES2016c.C.words.xml#id(ES2016c.C.words216)..id(ES2016c.C.words238)"/>
   </dact>
   <dact nite:id="ES2016c.C.dialog-act.dharshi.24">
      <nite:pointer role="da-aspect"  href="da-types.xml#id(ami_da_4)"/>
      <nite:child href="ES2016c.C.words.xml#id(ES2016c.C.words239)..id(ES2016c.C.words266)"/>
   </dact>
   <dact nite:id="ES2016c.C.dialog-act.dharshi.25">
      <nite:pointer role="da-aspect"  href="da-types.xml#id(ami_da_4)"/>
      <nite:child href="ES2016c.C.words.xml#id(ES2016c.C.words267)..id(ES2016c.C.words282)"/>
   </dact>
   <dact nite:id="ES2016c.C.dialog-act.dharshi.26">
      <nite:pointer role="da-aspect"  href="da-types.xml#id(ami_da_4)"/>
      <nite:child href="ES2016c.C.words.xml#id(ES2016c.C.words283)..id(ES2016c.C.words292)"/>
   </dact>
   <dact nite:id="ES2016c.C.dialog-act.dharshi.27">
      <nite:pointer role="da-aspect"  href="da-types.xml#id(ami_da_4)"/>
      <nite:child href="ES2016c.C.words.xml#id(ES2016c.C.words293)..id(ES2016c.C.words313)"/>
   </dact>
   <dact nite:id="ES2016c.C.dialog-act.dharshi.28">
      <nite:pointer role="da-aspect"  href="da-types.xml#id(ami_da_2)"/>
      <nite:child href="ES2016c.C.words.xml#id(ES2016c.C.words314)..id(ES2016c.C.words317)"/>
   </dact>
   <dact nite:id="ES2016c.C.dialog-act.dharshi.29">
      <nite:pointer role="da-aspect"  href="da-types.xml#id(ami_da_4)"/>
      <nite:child href="ES2016c.C.words.xml#id(ES2016c.C.words318)..id(ES2016c.C.words323)"/>
   </dact>
   <dact nite:id="ES2016c.C.dialog-act.dharshi.30">
      <nite:pointer role="da-aspect"  href="da-types.xml#id(ami_da_4)"/>
      <nite:child href="ES2016c.C.words.xml#id(ES2016c.C.words324)..id(ES2016c.C.words333)"/>
   </dact>
   <dact nite:id="ES2016c.C.dialog-act.dharshi.31">
      <nite:pointer role="da-aspect"  href="da-types.xml#id(ami_da_4)"/>
      <nite:child href="ES2016c.C.words.xml#id(ES2016c.C.words334)..id(ES2016c.C.words356)"/>
   </dact>
   <dact nite:id="ES2016c.C.dialog-act.dharshi.32">
      <nite:pointer role="da-aspect"  href="da-types.xml#id(ami_da_4)"/>
      <nite:child href="ES2016c.C.words.xml#id(ES2016c.C.words357)..id(ES2016c.C.words374)"/>
   </dact>
   <dact nite:id="ES2016c.C.dialog-act.dharshi.33">
      <nite:pointer role="da-aspect"  href="da-types.xml#id(ami_da_4)"/>
      <nite:child href="ES2016c.C.words.xml#id(ES2016c.C.words375)..id(ES2016c.C.words380)"/>
   </dact>
   <dact nite:id="ES2016c.C.dialog-act.dharshi.34">
      <nite:pointer role="da-aspect"  href="da-types.xml#id(ami_da_4)"/>
      <nite:child href="ES2016c.C.words.xml#id(ES2016c.C.words381)..id(ES2016c.C.words413)"/>
   </dact>
   <dact nite:id="ES2016c.C.dialog-act.dharshi.35">
      <nite:pointer role="da-aspect"  href="da-types.xml#id(ami_da_4)"/>
      <nite:child href="ES2016c.C.words.xml#id(ES2016c.C.words414)..id(ES2016c.C.words422)"/>
   </dact>
   <dact nite:id="ES2016c.C.dialog-act.dharshi.36">
      <nite:pointer role="da-aspect"  href="da-types.xml#id(ami_da_4)"/>
      <nite:child href="ES2016c.C.words.xml#id(ES2016c.C.words423)..id(ES2016c.C.words432)"/>
   </dact>
   <dact nite:id="ES2016c.C.dialog-act.dharshi.37">
      <nite:pointer role="da-aspect"  href="da-types.xml#id(ami_da_4)"/>
      <nite:child href="ES2016c.C.words.xml#id(ES2016c.C.words433)..id(ES2016c.C.words447)"/>
   </dact>
   <dact nite:id="ES2016c.C.dialog-act.dharshi.38">
      <nite:pointer role="da-aspect"  href="da-types.xml#id(ami_da_9)"/>
      <nite:child href="ES2016c.C.words.xml#id(ES2016c.C.words448)..id(ES2016c.C.words451)"/>
   </dact>
   <dact nite:id="ES2016c.C.dialog-act.dharshi.39">
      <nite:pointer role="da-aspect"  href="da-types.xml#id(ami_da_4)"/>
      <nite:child href="ES2016c.C.words.xml#id(ES2016c.C.words452)..id(ES2016c.C.words471)"/>
   </dact>
   <dact nite:id="ES2016c.C.dialog-act.dharshi.40">
      <nite:pointer role="da-aspect"  href="da-types.xml#id(ami_da_4)"/>
      <nite:child href="ES2016c.C.words.xml#id(ES2016c.C.words472)..id(ES2016c.C.words477)"/>
   </dact>
   <dact nite:id="ES2016c.C.dialog-act.dharshi.41">
      <nite:pointer role="da-aspect"  href="da-types.xml#id(ami_da_9)"/>
      <nite:child href="ES2016c.C.words.xml#id(ES2016c.C.words478)..id(ES2016c.C.words482)"/>
   </dact>
   <dact nite:id="ES2016c.C.dialog-act.dharshi.42">
      <nite:pointer role="da-aspect"  href="da-types.xml#id(ami_da_4)"/>
      <nite:child href="ES2016c.C.words.xml#id(ES2016c.C.words483)..id(ES2016c.C.words497)"/>
   </dact>
   <dact nite:id="ES2016c.C.dialog-act.dharshi.43">
      <nite:pointer role="da-aspect"  href="da-types.xml#id(ami_da_4)"/>
      <nite:child href="ES2016c.C.words.xml#id(ES2016c.C.words498)..id(ES2016c.C.words514)"/>
   </dact>
   <dact nite:id="ES2016c.C.dialog-act.dharshi.44">
      <nite:pointer role="da-aspect"  href="da-types.xml#id(ami_da_4)"/>
      <nite:child href="ES2016c.C.words.xml#id(ES2016c.C.words515)..id(ES2016c.C.words535)"/>
   </dact>
   <dact nite:id="ES2016c.C.dialog-act.dharshi.45">
      <nite:pointer role="da-aspect"  href="da-types.xml#id(ami_da_4)"/>
      <nite:child href="ES2016c.C.words.xml#id(ES2016c.C.words536)..id(ES2016c.C.words552)"/>
   </dact>
   <dact nite:id="ES2016c.C.dialog-act.dharshi.46">
      <nite:pointer role="da-aspect"  href="da-types.xml#id(ami_da_4)"/>
      <nite:child href="ES2016c.C.words.xml#id(ES2016c.C.words553)..id(ES2016c.C.words575)"/>
   </dact>
   <dact nite:id="ES2016c.C.dialog-act.dharshi.47">
      <nite:pointer role="da-aspect"  href="da-types.xml#id(ami_da_6)"/>
      <nite:child href="ES2016c.C.words.xml#id(ES2016c.C.words576)..id(ES2016c.C.words587)"/>
   </dact>
   <dact nite:id="ES2016c.C.dialog-act.dharshi.48">
      <nite:pointer role="da-aspect"  href="da-types.xml#id(ami_da_4)"/>
      <nite:child href="ES2016c.C.words.xml#id(ES2016c.C.words588)..id(ES2016c.C.words626)"/>
   </dact>
   <dact nite:id="ES2016c.C.dialog-act.dharshi.49">
      <nite:pointer role="da-aspect"  href="da-types.xml#id(ami_da_4)"/>
      <nite:child href="ES2016c.C.words.xml#id(ES2016c.C.words627)..id(ES2016c.C.words648)"/>
   </dact>
   <dact nite:id="ES2016c.C.dialog-act.dharshi.50">
      <nite:pointer role="da-aspect"  href="da-types.xml#id(ami_da_4)"/>
      <nite:child href="ES2016c.C.words.xml#id(ES2016c.C.words649)..id(ES2016c.C.words665)"/>
   </dact>
   <dact nite:id="ES2016c.C.dialog-act.dharshi.51">
      <nite:pointer role="da-aspect"  href="da-types.xml#id(ami_da_6)"/>
      <nite:child href="ES2016c.C.words.xml#id(ES2016c.C.words666)..id(ES2016c.C.words686)"/>
   </dact>
   <dact nite:id="ES2016c.C.dialog-act.dharshi.53">
      <nite:pointer role="da-aspect"  href="da-types.xml#id(ami_da_4)"/>
      <nite:child href="ES2016c.C.words.xml#id(ES2016c.C.words687)..id(ES2016c.C.words705)"/>
   </dact>
   <dact nite:id="ES2016c.C.dialog-act.dharshi.54">
      <nite:pointer role="da-aspect"  href="da-types.xml#id(ami_da_6)"/>
      <nite:child href="ES2016c.C.words.xml#id(ES2016c.C.words706)..id(ES2016c.C.words725)"/>
   </dact>
   <dact nite:id="ES2016c.C.dialog-act.dharshi.55">
      <nite:pointer role="da-aspect"  href="da-types.xml#id(ami_da_6)"/>
      <nite:child href="ES2016c.C.words.xml#id(ES2016c.C.words726)..id(ES2016c.C.words747)"/>
   </dact>
   <dact nite:id="ES2016c.C.dialog-act.dharshi.56">
      <nite:pointer role="da-aspect"  href="da-types.xml#id(ami_da_3)"/>
      <nite:child href="ES2016c.C.words.xml#id(ES2016c.C.words748)..id(ES2016c.C.words751)"/>
   </dact>
   <dact nite:id="ES2016c.C.dialog-act.dharshi.57">
      <nite:pointer role="da-aspect"  href="da-types.xml#id(ami_da_6)"/>
      <nite:child href="ES2016c.C.words.xml#id(ES2016c.C.words752)..id(ES2016c.C.words782)"/>
   </dact>
   <dact nite:id="ES2016c.C.dialog-act.dharshi.58">
      <nite:pointer role="da-aspect"  href="da-types.xml#id(ami_da_4)"/>
      <nite:child href="ES2016c.C.words.xml#id(ES2016c.C.words783)..id(ES2016c.C.words792)"/>
   </dact>
   <dact nite:id="ES2016c.C.dialog-act.dharshi.59">
      <nite:pointer role="da-aspect"  href="da-types.xml#id(ami_da_4)"/>
      <nite:child href="ES2016c.C.words.xml#id(ES2016c.C.words793)..id(ES2016c.C.words803)"/>
   </dact>
   <dact nite:id="ES2016c.C.dialog-act.dharshi.60">
      <nite:pointer role="da-aspect"  href="da-types.xml#id(ami_da_4)"/>
      <nite:child href="ES2016c.C.words.xml#id(ES2016c.C.words804)..id(ES2016c.C.words808)"/>
   </dact>
   <dact nite:id="ES2016c.C.dialog-act.dharshi.61">
      <nite:pointer role="da-aspect"  href="da-types.xml#id(ami_da_3)"/>
      <nite:child href="ES2016c.C.words.xml#id(ES2016c.C.words809)..id(ES2016c.C.words812)"/>
   </dact>
   <dact nite:id="ES2016c.C.dialog-act.dharshi.67">
      <nite:pointer role="da-aspect"  href="da-types.xml#id(ami_da_9)"/>
      <nite:child href="ES2016c.C.words.xml#id(ES2016c.C.words813)..id(ES2016c.C.words815)"/>
   </dact>
   <dact nite:id="ES2016c.C.dialog-act.dharshi.62">
      <nite:pointer role="da-aspect"  href="da-types.xml#id(ami_da_3)"/>
      <nite:child href="ES2016c.C.words.xml#id(ES2016c.C.words816)..id(ES2016c.C.words818)"/>
   </dact>
   <dact nite:id="ES2016c.C.dialog-act.dharshi.63">
      <nite:pointer role="da-aspect"  href="da-types.xml#id(ami_da_16)"/>
      <nite:child href="ES2016c.C.words.xml#id(ES2016c.C.words819)..id(ES2016c.C.words825)"/>
   </dact>
   <dact nite:id="ES2016c.C.dialog-act.dharshi.64">
      <nite:pointer role="da-aspect"  href="da-types.xml#id(ami_da_7)"/>
      <nite:child href="ES2016c.C.words.xml#id(ES2016c.C.words826)..id(ES2016c.C.words832)"/>
   </dact>
   <dact nite:id="ES2016c.C.dialog-act.dharshi.65">
      <nite:pointer role="da-aspect"  href="da-types.xml#id(ami_da_4)"/>
      <nite:child href="ES2016c.C.words.xml#id(ES2016c.C.words833)..id(ES2016c.C.words841)"/>
   </dact>
   <dact nite:id="ES2016c.C.dialog-act.dharshi.66">
      <nite:pointer role="da-aspect"  href="da-types.xml#id(ami_da_4)"/>
      <nite:child href="ES2016c.C.words.xml#id(ES2016c.C.words842)..id(ES2016c.C.words844)"/>
   </dact>
   <dact nite:id="ES2016c.C.dialog-act.dharshi.68">
      <nite:pointer role="da-aspect"  href="da-types.xml#id(ami_da_9)"/>
      <nite:child href="ES2016c.C.words.xml#id(ES2016c.C.words845)..id(ES2016c.C.words857)"/>
   </dact>
   <dact nite:id="ES2016c.C.dialog-act.dharshi.69">
      <nite:pointer role="da-aspect"  href="da-types.xml#id(ami_da_9)"/>
      <nite:child href="ES2016c.C.words.xml#id(ES2016c.C.words858)..id(ES2016c.C.words861)"/>
   </dact>
   <dact nite:id="ES2016c.C.dialog-act.dharshi.73">
      <nite:pointer role="da-aspect"  href="da-types.xml#id(ami_da_9)"/>
      <nite:child href="ES2016c.C.words.xml#id(ES2016c.C.words862)..id(ES2016c.C.words866)"/>
   </dact>
   <dact nite:id="ES2016c.C.dialog-act.dharshi.76">
      <nite:pointer role="da-aspect"  href="da-types.xml#id(ami_da_9)"/>
      <nite:child href="ES2016c.C.words.xml#id(ES2016c.C.words867)..id(ES2016c.C.words868)"/>
   </dact>
   <dact nite:id="ES2016c.C.dialog-act.dharshi.77">
      <nite:pointer role="da-aspect"  href="da-types.xml#id(ami_da_4)"/>
      <nite:child href="ES2016c.C.words.xml#id(ES2016c.C.words869)..id(ES2016c.C.words870)"/>
   </dact>
   <dact nite:id="ES2016c.C.dialog-act.dharshi.72">
      <nite:pointer role="da-aspect"  href="da-types.xml#id(ami_da_3)"/>
      <nite:child href="ES2016c.C.words.xml#id(ES2016c.C.words871)..id(ES2016c.C.words874)"/>
   </dact>
   <dact nite:id="ES2016c.C.dialog-act.dharshi.70">
      <nite:pointer role="da-aspect"  href="da-types.xml#id(ami_da_3)"/>
      <nite:child href="ES2016c.C.words.xml#id(ES2016c.C.words875)..id(ES2016c.C.words876)"/>
   </dact>
   <dact nite:id="ES2016c.C.dialog-act.dharshi.74">
      <nite:pointer role="da-aspect"  href="da-types.xml#id(ami_da_16)"/>
      <nite:child href="ES2016c.C.words.xml#id(ES2016c.C.words877)..id(ES2016c.C.words881)"/>
   </dact>
   <dact nite:id="ES2016c.C.dialog-act.dharshi.78">
      <nite:pointer role="da-aspect"  href="da-types.xml#id(ami_da_3)"/>
      <nite:child href="ES2016c.C.words.xml#id(ES2016c.C.words882)"/>
   </dact>
   <dact nite:id="ES2016c.C.dialog-act.dharshi.79">
      <nite:pointer role="da-aspect"  href="da-types.xml#id(ami_da_3)"/>
      <nite:child href="ES2016c.C.words.xml#id(ES2016c.C.words883)"/>
   </dact>
   <dact nite:id="ES2016c.C.dialog-act.dharshi.80">
      <nite:pointer role="da-aspect"  href="da-types.xml#id(ami_da_1)"/>
      <nite:child href="ES2016c.C.words.xml#id(ES2016c.C.words884)..id(ES2016c.C.words885)"/>
   </dact>
   <dact nite:id="ES2016c.C.dialog-act.dharshi.81">
      <nite:pointer role="da-aspect"  href="da-types.xml#id(ami_da_5)"/>
      <nite:child href="ES2016c.C.words.xml#id(ES2016c.C.words886)..id(ES2016c.C.words895)"/>
   </dact>
   <dact nite:id="ES2016c.C.dialog-act.dharshi.83">
      <nite:pointer role="da-aspect"  href="da-types.xml#id(ami_da_9)"/>
      <nite:child href="ES2016c.C.words.xml#id(ES2016c.C.words896)..id(ES2016c.C.words899)"/>
   </dact>
   <dact nite:id="ES2016c.C.dialog-act.dharshi.82">
      <nite:pointer role="da-aspect"  href="da-types.xml#id(ami_da_9)"/>
      <nite:child href="ES2016c.C.words.xml#id(ES2016c.C.words900)..id(ES2016c.C.words901)"/>
   </dact>
   <dact nite:id="ES2016c.C.dialog-act.dharshi.84">
      <nite:pointer role="da-aspect"  href="da-types.xml#id(ami_da_1)"/>
      <nite:child href="ES2016c.C.words.xml#id(ES2016c.C.words902)..id(ES2016c.C.words903)"/>
   </dact>
   <dact nite:id="ES2016c.C.dialog-act.dharshi.85">
      <nite:pointer role="da-aspect"  href="da-types.xml#id(ami_da_9)"/>
      <nite:child href="ES2016c.C.words.xml#id(ES2016c.C.words904)..id(ES2016c.C.words905)"/>
   </dact>
   <dact nite:id="ES2016c.C.dialog-act.dharshi.86">
      <nite:pointer role="da-aspect"  href="da-types.xml#id(ami_da_1)"/>
      <nite:child href="ES2016c.C.words.xml#id(ES2016c.C.words906)..id(ES2016c.C.words907)"/>
   </dact>
   <dact nite:id="ES2016c.C.dialog-act.dharshi.87">
      <nite:pointer role="da-aspect"  href="da-types.xml#id(ami_da_4)"/>
      <nite:child href="ES2016c.C.words.xml#id(ES2016c.C.words908)..id(ES2016c.C.words919)"/>
   </dact>
   <dact nite:id="ES2016c.C.dialog-act.dharshi.88">
      <nite:pointer role="da-aspect"  href="da-types.xml#id(ami_da_4)"/>
      <nite:child href="ES2016c.C.words.xml#id(ES2016c.C.words920)..id(ES2016c.C.words956)"/>
   </dact>
   <dact nite:id="ES2016c.C.dialog-act.dharshi.89">
      <nite:pointer role="da-aspect"  href="da-types.xml#id(ami_da_5)"/>
      <nite:child href="ES2016c.C.words.xml#id(ES2016c.C.words957)..id(ES2016c.C.words974)"/>
   </dact>
   <dact nite:id="ES2016c.C.dialog-act.dharshi.90">
      <nite:pointer role="da-aspect"  href="da-types.xml#id(ami_da_5)"/>
      <nite:child href="ES2016c.C.words.xml#id(ES2016c.C.words975)..id(ES2016c.C.words982)"/>
   </dact>
   <dact nite:id="ES2016c.C.dialog-act.dharshi.91">
      <nite:pointer role="da-aspect"  href="da-types.xml#id(ami_da_9)"/>
      <nite:child href="ES2016c.C.words.xml#id(ES2016c.C.words983)..id(ES2016c.C.words989)"/>
   </dact>
   <dact nite:id="ES2016c.C.dialog-act.dharshi.92">
      <nite:pointer role="da-aspect"  href="da-types.xml#id(ami_da_3)"/>
      <nite:child href="ES2016c.C.words.xml#id(ES2016c.C.words990)"/>
   </dact>
   <dact nite:id="ES2016c.C.dialog-act.dharshi.93">
      <nite:pointer role="da-aspect"  href="da-types.xml#id(ami_da_3)"/>
      <nite:child href="ES2016c.C.words.xml#id(ES2016c.C.words991)"/>
   </dact>
   <dact nite:id="ES2016c.C.dialog-act.dharshi.94">
      <nite:pointer role="da-aspect"  href="da-types.xml#id(ami_da_3)"/>
      <nite:child href="ES2016c.C.words.xml#id(ES2016c.C.words992)..id(ES2016c.C.words994)"/>
   </dact>
   <dact nite:id="ES2016c.C.dialog-act.dharshi.95">
      <nite:pointer role="da-aspect"  href="da-types.xml#id(ami_da_5)"/>
      <nite:child href="ES2016c.C.words.xml#id(ES2016c.C.words995)..id(ES2016c.C.words1011)"/>
   </dact>
   <dact nite:id="ES2016c.C.dialog-act.dharshi.96">
      <nite:pointer role="da-aspect"  href="da-types.xml#id(ami_da_5)"/>
      <nite:child href="ES2016c.C.words.xml#id(ES2016c.C.words1012)..id(ES2016c.C.words1015)"/>
   </dact>
   <dact nite:id="ES2016c.C.dialog-act.dharshi.97">
      <nite:pointer role="da-aspect"  href="da-types.xml#id(ami_da_9)"/>
      <nite:child href="ES2016c.C.words.xml#id(ES2016c.C.words1016)..id(ES2016c.C.words1017)"/>
   </dact>
   <dact nite:id="ES2016c.C.dialog-act.dharshi.98">
      <nite:pointer role="da-aspect"  href="da-types.xml#id(ami_da_1)"/>
      <nite:child href="ES2016c.C.words.xml#id(ES2016c.C.words1018)..id(ES2016c.C.words1020)"/>
   </dact>
   <dact nite:id="ES2016c.C.dialog-act.dharshi.99">
      <nite:pointer role="da-aspect"  href="da-types.xml#id(ami_da_1)"/>
      <nite:child href="ES2016c.C.words.xml#id(ES2016c.C.words1021)..id(ES2016c.C.words1022)"/>
   </dact>
   <dact nite:id="ES2016c.C.dialog-act.dharshi.100">
      <nite:pointer role="da-aspect"  href="da-types.xml#id(ami_da_6)"/>
      <nite:child href="ES2016c.C.words.xml#id(ES2016c.C.words1023)..id(ES2016c.C.words1037)"/>
   </dact>
   <dact nite:id="ES2016c.C.dialog-act.dharshi.101">
      <nite:pointer role="da-aspect"  href="da-types.xml#id(ami_da_6)"/>
      <nite:child href="ES2016c.C.words.xml#id(ES2016c.C.words1038)..id(ES2016c.C.words1057)"/>
   </dact>
   <dact nite:id="ES2016c.C.dialog-act.dharshi.102">
      <nite:pointer role="da-aspect"  href="da-types.xml#id(ami_da_6)"/>
      <nite:child href="ES2016c.C.words.xml#id(ES2016c.C.words1058)..id(ES2016c.C.words1067)"/>
   </dact>
   <dact nite:id="ES2016c.C.dialog-act.dharshi.103">
      <nite:pointer role="da-aspect"  href="da-types.xml#id(ami_da_4)"/>
      <nite:child href="ES2016c.C.words.xml#id(ES2016c.C.words1068)..id(ES2016c.C.words1090)"/>
   </dact>
   <dact nite:id="ES2016c.C.dialog-act.dharshi.104">
      <nite:pointer role="da-aspect"  href="da-types.xml#id(ami_da_3)"/>
      <nite:child href="ES2016c.C.words.xml#id(ES2016c.C.words1091)..id(ES2016c.C.words1095)"/>
   </dact>
   <dact nite:id="ES2016c.C.dialog-act.dharshi.105">
      <nite:pointer role="da-aspect"  href="da-types.xml#id(ami_da_4)"/>
      <nite:child href="ES2016c.C.words.xml#id(ES2016c.C.words1096)..id(ES2016c.C.words1101)"/>
   </dact>
   <dact nite:id="ES2016c.C.dialog-act.dharshi.106">
      <nite:pointer role="da-aspect"  href="da-types.xml#id(ami_da_4)"/>
      <nite:child href="ES2016c.C.words.xml#id(ES2016c.C.words1102)..id(ES2016c.C.words1113)"/>
   </dact>
   <dact nite:id="ES2016c.C.dialog-act.dharshi.107">
      <nite:pointer role="da-aspect"  href="da-types.xml#id(ami_da_1)"/>
      <nite:child href="ES2016c.C.words.xml#id(ES2016c.C.words1114)..id(ES2016c.C.words1115)"/>
   </dact>
   <dact nite:id="ES2016c.C.dialog-act.dharshi.108">
      <nite:pointer role="da-aspect"  href="da-types.xml#id(ami_da_1)"/>
      <nite:child href="ES2016c.C.words.xml#id(ES2016c.C.words1116)..id(ES2016c.C.words1117)"/>
   </dact>
   <dact nite:id="ES2016c.C.dialog-act.dharshi.109">
      <nite:pointer role="da-aspect"  href="da-types.xml#id(ami_da_3)"/>
      <nite:child href="ES2016c.C.words.xml#id(ES2016c.C.words1118)"/>
   </dact>
   <dact nite:id="ES2016c.C.dialog-act.dharshi.110">
      <nite:pointer role="da-aspect"  href="da-types.xml#id(ami_da_6)"/>
      <nite:child href="ES2016c.C.words.xml#id(ES2016c.C.words1119)..id(ES2016c.C.words1131)"/>
   </dact>
   <dact nite:id="ES2016c.C.dialog-act.dharshi.111">
      <nite:pointer role="da-aspect"  href="da-types.xml#id(ami_da_6)"/>
      <nite:child href="ES2016c.C.words.xml#id(ES2016c.C.words1132)..id(ES2016c.C.words1136)"/>
   </dact>
   <dact nite:id="ES2016c.C.dialog-act.dharshi.112">
      <nite:pointer role="da-aspect"  href="da-types.xml#id(ami_da_4)"/>
      <nite:child href="ES2016c.C.words.xml#id(ES2016c.C.words1137)..id(ES2016c.C.words1145)"/>
   </dact>
   <dact nite:id="ES2016c.C.dialog-act.dharshi.113">
      <nite:pointer role="da-aspect"  href="da-types.xml#id(ami_da_9)"/>
      <nite:child href="ES2016c.C.words.xml#id(ES2016c.C.words1146)..id(ES2016c.C.words1151)"/>
   </dact>
   <dact nite:id="ES2016c.C.dialog-act.dharshi.114">
      <nite:pointer role="da-aspect"  href="da-types.xml#id(ami_da_4)"/>
      <nite:child href="ES2016c.C.words.xml#id(ES2016c.C.words1152)..id(ES2016c.C.words1155)"/>
   </dact>
   <dact nite:id="ES2016c.C.dialog-act.dharshi.116">
      <nite:pointer role="da-aspect"  href="da-types.xml#id(ami_da_1)"/>
      <nite:child href="ES2016c.C.words.xml#id(ES2016c.C.words1156)..id(ES2016c.C.words1157)"/>
   </dact>
   <dact nite:id="ES2016c.C.dialog-act.dharshi.115">
      <nite:pointer role="da-aspect"  href="da-types.xml#id(ami_da_3)"/>
      <nite:child href="ES2016c.C.words.xml#id(ES2016c.C.words1158)..id(ES2016c.C.words1159)"/>
   </dact>
   <dact nite:id="ES2016c.C.dialog-act.dharshi.117">
      <nite:pointer role="da-aspect"  href="da-types.xml#id(ami_da_9)"/>
      <nite:child href="ES2016c.C.words.xml#id(ES2016c.C.words1160)..id(ES2016c.C.words1161)"/>
   </dact>
   <dact nite:id="ES2016c.C.dialog-act.dharshi.118">
      <nite:pointer role="da-aspect"  href="da-types.xml#id(ami_da_1)"/>
      <nite:child href="ES2016c.C.words.xml#id(ES2016c.C.words1162)..id(ES2016c.C.words1163)"/>
   </dact>
   <dact nite:id="ES2016c.C.dialog-act.dharshi.119">
      <nite:pointer role="da-aspect"  href="da-types.xml#id(ami_da_1)"/>
      <nite:child href="ES2016c.C.words.xml#id(ES2016c.C.words1164)..id(ES2016c.C.words1165)"/>
   </dact>
   <dact nite:id="ES2016c.C.dialog-act.dharshi.120">
      <nite:pointer role="da-aspect"  href="da-types.xml#id(ami_da_6)"/>
      <nite:child href="ES2016c.C.words.xml#id(ES2016c.C.words1166)..id(ES2016c.C.words1182)"/>
   </dact>
   <dact nite:id="ES2016c.C.dialog-act.dharshi.121">
      <nite:pointer role="da-aspect"  href="da-types.xml#id(ami_da_1)"/>
      <nite:child href="ES2016c.C.words.xml#id(ES2016c.C.words1183)..id(ES2016c.C.words1185)"/>
   </dact>
   <dact nite:id="ES2016c.C.dialog-act.dharshi.122">
      <nite:pointer role="da-aspect"  href="da-types.xml#id(ami_da_2)"/>
      <nite:child href="ES2016c.C.words.xml#id(ES2016c.C.words1186)..id(ES2016c.C.words1189)"/>
   </dact>
   <dact nite:id="ES2016c.C.dialog-act.dharshi.123">
      <nite:pointer role="da-aspect"  href="da-types.xml#id(ami_da_6)"/>
      <nite:child href="ES2016c.C.words.xml#id(ES2016c.C.words1190)..id(ES2016c.C.words1196)"/>
   </dact>
   <dact nite:id="ES2016c.C.dialog-act.dharshi.124">
      <nite:pointer role="da-aspect"  href="da-types.xml#id(ami_da_1)"/>
      <nite:child href="ES2016c.C.words.xml#id(ES2016c.C.words1197)..id(ES2016c.C.words1198)"/>
   </dact>
   <dact nite:id="ES2016c.C.dialog-act.dharshi.125">
      <nite:pointer role="da-aspect"  href="da-types.xml#id(ami_da_2)"/>
      <nite:child href="ES2016c.C.words.xml#id(ES2016c.C.words1199)..id(ES2016c.C.words1201)"/>
   </dact>
   <dact nite:id="ES2016c.C.dialog-act.dharshi.126">
      <nite:pointer role="da-aspect"  href="da-types.xml#id(ami_da_4)"/>
      <nite:child href="ES2016c.C.words.xml#id(ES2016c.C.words1202)..id(ES2016c.C.words1221)"/>
   </dact>
   <dact nite:id="ES2016c.C.dialog-act.dharshi.127">
      <nite:pointer role="da-aspect"  href="da-types.xml#id(ami_da_4)"/>
      <nite:child href="ES2016c.C.words.xml#id(ES2016c.C.words1222)..id(ES2016c.C.words1231)"/>
   </dact>
   <dact nite:id="ES2016c.C.dialog-act.dharshi.128">
      <nite:pointer role="da-aspect"  href="da-types.xml#id(ami_da_3)"/>
      <nite:child href="ES2016c.C.words.xml#id(ES2016c.C.words1232)"/>
   </dact>
   <dact nite:id="ES2016c.C.dialog-act.dharshi.129">
      <nite:pointer role="da-aspect"  href="da-types.xml#id(ami_da_1)"/>
      <nite:child href="ES2016c.C.words.xml#id(ES2016c.C.words1233)..id(ES2016c.C.words1234)"/>
   </dact>
   <dact nite:id="ES2016c.C.dialog-act.dharshi.130">
      <nite:pointer role="da-aspect"  href="da-types.xml#id(ami_da_1)"/>
      <nite:child href="ES2016c.C.words.xml#id(ES2016c.C.words1235)..id(ES2016c.C.words1236)"/>
   </dact>
   <dact nite:id="ES2016c.C.dialog-act.dharshi.131">
      <nite:pointer role="da-aspect"  href="da-types.xml#id(ami_da_4)"/>
      <nite:child href="ES2016c.C.words.xml#id(ES2016c.C.words1237)..id(ES2016c.C.words1252)"/>
   </dact>
   <dact nite:id="ES2016c.C.dialog-act.dharshi.132">
      <nite:pointer role="da-aspect"  href="da-types.xml#id(ami_da_4)"/>
      <nite:child href="ES2016c.C.words.xml#id(ES2016c.C.words1253)..id(ES2016c.C.words1261)"/>
   </dact>
   <dact nite:id="ES2016c.C.dialog-act.dharshi.133">
      <nite:pointer role="da-aspect"  href="da-types.xml#id(ami_da_1)"/>
      <nite:child href="ES2016c.C.words.xml#id(ES2016c.C.words1262)..id(ES2016c.C.words1263)"/>
   </dact>
   <dact nite:id="ES2016c.C.dialog-act.dharshi.134">
      <nite:pointer role="da-aspect"  href="da-types.xml#id(ami_da_1)"/>
      <nite:child href="ES2016c.C.words.xml#id(ES2016c.C.words1264)..id(ES2016c.C.words1265)"/>
   </dact>
   <dact nite:id="ES2016c.C.dialog-act.dharshi.135">
      <nite:pointer role="da-aspect"  href="da-types.xml#id(ami_da_3)"/>
      <nite:child href="ES2016c.C.words.xml#id(ES2016c.C.words1266)..id(ES2016c.C.words1267)"/>
   </dact>
   <dact nite:id="ES2016c.C.dialog-act.dharshi.136">
      <nite:pointer role="da-aspect"  href="da-types.xml#id(ami_da_3)"/>
      <nite:child href="ES2016c.C.words.xml#id(ES2016c.C.words1268)..id(ES2016c.C.words1270)"/>
   </dact>
   <dact nite:id="ES2016c.C.dialog-act.dharshi.137">
      <nite:pointer role="da-aspect"  href="da-types.xml#id(ami_da_9)"/>
      <nite:child href="ES2016c.C.words.xml#id(ES2016c.C.words1271)..id(ES2016c.C.words1279)"/>
   </dact>
   <dact nite:id="ES2016c.C.dialog-act.dharshi.139">
      <nite:pointer role="da-aspect"  href="da-types.xml#id(ami_da_1)"/>
      <nite:child href="ES2016c.C.words.xml#id(ES2016c.C.words1280)..id(ES2016c.C.words1281)"/>
   </dact>
   <dact nite:id="ES2016c.C.dialog-act.dharshi.142">
      <nite:pointer role="da-aspect"  href="da-types.xml#id(ami_da_1)"/>
      <nite:child href="ES2016c.C.words.xml#id(ES2016c.C.words1282)..id(ES2016c.C.words1283)"/>
   </dact>
   <dact nite:id="ES2016c.C.dialog-act.dharshi.143">
      <nite:pointer role="da-aspect"  href="da-types.xml#id(ami_da_4)"/>
      <nite:child href="ES2016c.C.words.xml#id(ES2016c.C.words1284)..id(ES2016c.C.words1288)"/>
   </dact>
   <dact nite:id="ES2016c.C.dialog-act.dharshi.144">
      <nite:pointer role="da-aspect"  href="da-types.xml#id(ami_da_3)"/>
      <nite:child href="ES2016c.C.words.xml#id(ES2016c.C.words1289)..id(ES2016c.C.words1291)"/>
   </dact>
   <dact nite:id="ES2016c.C.dialog-act.dharshi.141">
      <nite:pointer role="da-aspect"  href="da-types.xml#id(ami_da_3)"/>
      <nite:child href="ES2016c.C.words.xml#id(ES2016c.C.words1292)"/>
   </dact>
   <dact nite:id="ES2016c.C.dialog-act.dharshi.140">
      <nite:pointer role="da-aspect"  href="da-types.xml#id(ami_da_3)"/>
      <nite:child href="ES2016c.C.words.xml#id(ES2016c.C.words1293)"/>
   </dact>
</nite:root>