<?xml version="1.0" encoding="ISO-8859-1" standalone="yes"?>
<nite:root nite:id="TS3005c.D.ne" xmlns:nite="http://nite.sourceforge.net/">
   <named-entity nite:id="TS3005c.D.ne.1">
      <nite:pointer role="type"  href="ne-types.xml#id(ne_47)"/>
      <nite:child href="TS3005c.D.words.xml#id(TS3005c.D.words6)"/>
   </named-entity>
   <named-entity nite:id="TS3005c.D.ne.2">
      <nite:pointer role="type"  href="ne-types.xml#id(ne_50)"/>
      <nite:child href="TS3005c.D.words.xml#id(TS3005c.D.words13)"/>
   </named-entity>
   <named-entity nite:id="TS3005c.D.ne.3">
      <nite:pointer role="type"  href="ne-types.xml#id(ne_50)"/>
      <nite:child href="TS3005c.D.words.xml#id(TS3005c.D.words16)"/>
   </named-entity>
   <named-entity nite:id="TS3005c.D.ne.4">
      <nite:pointer role="type"  href="ne-types.xml#id(ne_47)"/>
      <nite:child href="TS3005c.D.words.xml#id(TS3005c.D.words64)"/>
   </named-entity>
   <named-entity nite:id="TS3005c.D.ne.5">
      <nite:pointer role="type"  href="ne-types.xml#id(ne_34)"/>
      <nite:child href="TS3005c.D.words.xml#id(TS3005c.D.words66)"/>
   </named-entity>
   <named-entity nite:id="TS3005c.D.ne.6">
      <nite:pointer role="type"  href="ne-types.xml#id(ne_34)"/>
      <nite:child href="TS3005c.D.words.xml#id(TS3005c.D.words246)"/>
   </named-entity>
   <named-entity nite:id="TS3005c.D.ne.7">
      <nite:pointer role="type"  href="ne-types.xml#id(ne_34)"/>
      <nite:child href="TS3005c.D.words.xml#id(TS3005c.D.words249)"/>
   </named-entity>
   <named-entity nite:id="TS3005c.D.ne.8">
      <nite:pointer role="type"  href="ne-types.xml#id(ne_50)"/>
      <nite:child href="TS3005c.D.words.xml#id(TS3005c.D.words276)"/>
   </named-entity>
   <named-entity nite:id="TS3005c.D.ne.9">
      <nite:pointer role="type"  href="ne-types.xml#id(ne_50)"/>
      <nite:child href="TS3005c.D.words.xml#id(TS3005c.D.words280)..id(TS3005c.D.words281)"/>
   </named-entity>
   <named-entity nite:id="TS3005c.D.ne.10">
      <nite:pointer role="type"  href="ne-types.xml#id(ne_50)"/>
      <nite:child href="TS3005c.D.words.xml#id(TS3005c.D.words284)..id(TS3005c.D.words285)"/>
   </named-entity>
   <named-entity nite:id="TS3005c.D.ne.11">
      <nite:pointer role="type"  href="ne-types.xml#id(ne_60)"/>
      <nite:child href="TS3005c.D.words.xml#id(TS3005c.D.words295)"/>
   </named-entity>
   <named-entity nite:id="TS3005c.D.ne.12">
      <nite:pointer role="type"  href="ne-types.xml#id(ne_70)"/>
      <nite:child href="TS3005c.D.words.xml#id(TS3005c.D.words305)"/>
   </named-entity>
   <named-entity nite:id="TS3005c.D.ne.13">
      <nite:pointer role="type"  href="ne-types.xml#id(ne_113)"/>
      <nite:child href="TS3005c.D.words.xml#id(TS3005c.D.words319)..id(TS3005c.D.words320)"/>
   </named-entity>
   <named-entity nite:id="TS3005c.D.ne.14">
      <nite:pointer role="type"  href="ne-types.xml#id(ne_22)"/>
      <nite:child href="TS3005c.D.words.xml#id(TS3005c.D.words336)"/>
   </named-entity>
   <named-entity nite:id="TS3005c.D.ne.15">
      <nite:pointer role="type"  href="ne-types.xml#id(ne_70)"/>
      <nite:child href="TS3005c.D.words.xml#id(TS3005c.D.words339)"/>
   </named-entity>
   <named-entity nite:id="TS3005c.D.ne.16">
      <nite:pointer role="type"  href="ne-types.xml#id(ne_50)"/>
      <nite:child href="TS3005c.D.words.xml#id(TS3005c.D.words341)..id(TS3005c.D.words342)"/>
   </named-entity>
   <named-entity nite:id="TS3005c.D.ne.17">
      <nite:pointer role="type"  href="ne-types.xml#id(ne_50)"/>
      <nite:child href="TS3005c.D.words.xml#id(TS3005c.D.words344)"/>
   </named-entity>
   <named-entity nite:id="TS3005c.D.ne.18">
      <nite:pointer role="type"  href="ne-types.xml#id(ne_50)"/>
      <nite:child href="TS3005c.D.words.xml#id(TS3005c.D.words346)..id(TS3005c.D.words347)"/>
   </named-entity>
   <named-entity nite:id="TS3005c.D.ne.19">
      <nite:pointer role="type"  href="ne-types.xml#id(ne_60)"/>
      <nite:child href="TS3005c.D.words.xml#id(TS3005c.D.words353)"/>
   </named-entity>
   <named-entity nite:id="TS3005c.D.ne.20">
      <nite:pointer role="type"  href="ne-types.xml#id(ne_60)"/>
      <nite:child href="TS3005c.D.words.xml#id(TS3005c.D.words356)"/>
   </named-entity>
   <named-entity nite:id="TS3005c.D.ne.21">
      <nite:pointer role="type"  href="ne-types.xml#id(ne_70)"/>
      <nite:child href="TS3005c.D.words.xml#id(TS3005c.D.words363)"/>
   </named-entity>
   <named-entity nite:id="TS3005c.D.ne.22">
      <nite:pointer role="type"  href="ne-types.xml#id(ne_70)"/>
      <nite:child href="TS3005c.D.words.xml#id(TS3005c.D.words366)"/>
   </named-entity>
   <named-entity nite:id="TS3005c.D.ne.23">
      <nite:pointer role="type"  href="ne-types.xml#id(ne_50)"/>
      <nite:child href="TS3005c.D.words.xml#id(TS3005c.D.words386)"/>
   </named-entity>
   <named-entity nite:id="TS3005c.D.ne.24">
      <nite:pointer role="type"  href="ne-types.xml#id(ne_50)"/>
      <nite:child href="TS3005c.D.words.xml#id(TS3005c.D.words398)"/>
   </named-entity>
   <named-entity nite:id="TS3005c.D.ne.25">
      <nite:pointer role="type"  href="ne-types.xml#id(ne_50)"/>
      <nite:child href="TS3005c.D.words.xml#id(TS3005c.D.words401)"/>
   </named-entity>
   <named-entity nite:id="TS3005c.D.ne.26">
      <nite:pointer role="type"  href="ne-types.xml#id(ne_50)"/>
      <nite:child href="TS3005c.D.words.xml#id(TS3005c.D.words404)"/>
   </named-entity>
   <named-entity nite:id="TS3005c.D.ne.27">
      <nite:pointer role="type"  href="ne-types.xml#id(ne_50)"/>
      <nite:child href="TS3005c.D.words.xml#id(TS3005c.D.words407)"/>
   </named-entity>
   <named-entity nite:id="TS3005c.D.ne.28">
      <nite:pointer role="type"  href="ne-types.xml#id(ne_47)"/>
      <nite:child href="TS3005c.D.words.xml#id(TS3005c.D.words444)"/>
   </named-entity>
   <named-entity nite:id="TS3005c.D.ne.29">
      <nite:pointer role="type"  href="ne-types.xml#id(ne_50)"/>
      <nite:child href="TS3005c.D.words.xml#id(TS3005c.D.words451)"/>
   </named-entity>
   <named-entity nite:id="TS3005c.D.ne.30">
      <nite:pointer role="type"  href="ne-types.xml#id(ne_34)"/>
      <nite:child href="TS3005c.D.words.xml#id(TS3005c.D.words470)"/>
   </named-entity>
   <named-entity nite:id="TS3005c.D.ne.31">
      <nite:pointer role="type"  href="ne-types.xml#id(ne_34)"/>
      <nite:child href="TS3005c.D.words.xml#id(TS3005c.D.words475)"/>
   </named-entity>
   <named-entity nite:id="TS3005c.D.ne.32">
      <nite:pointer role="type"  href="ne-types.xml#id(ne_34)"/>
      <nite:child href="TS3005c.D.words.xml#id(TS3005c.D.words481)"/>
   </named-entity>
   <named-entity nite:id="TS3005c.D.ne.33">
      <nite:pointer role="type"  href="ne-types.xml#id(ne_60)"/>
      <nite:child href="TS3005c.D.words.xml#id(TS3005c.D.words498)"/>
   </named-entity>
   <named-entity nite:id="TS3005c.D.ne.34">
      <nite:pointer role="type"  href="ne-types.xml#id(ne_60)"/>
      <nite:child href="TS3005c.D.words.xml#id(TS3005c.D.words529)"/>
   </named-entity>
   <named-entity nite:id="TS3005c.D.ne.35">
      <nite:pointer role="type"  href="ne-types.xml#id(ne_60)"/>
      <nite:child href="TS3005c.D.words.xml#id(TS3005c.D.words530)"/>
   </named-entity>
   <named-entity nite:id="TS3005c.D.ne.36">
      <nite:pointer role="type"  href="ne-types.xml#id(ne_22)"/>
      <nite:child href="TS3005c.D.words.xml#id(TS3005c.D.words576)"/>
   </named-entity>
   <named-entity nite:id="TS3005c.D.ne.37">
      <nite:pointer role="type"  href="ne-types.xml#id(ne_50)"/>
      <nite:child href="TS3005c.D.words.xml#id(TS3005c.D.words579)"/>
   </named-entity>
   <named-entity nite:id="TS3005c.D.ne.38">
      <nite:pointer role="type"  href="ne-types.xml#id(ne_50)"/>
      <nite:child href="TS3005c.D.words.xml#id(TS3005c.D.words581)"/>
   </named-entity>
   <named-entity nite:id="TS3005c.D.ne.39">
      <nite:pointer role="type"  href="ne-types.xml#id(ne_70)"/>
      <nite:child href="TS3005c.D.words.xml#id(TS3005c.D.words586)"/>
   </named-entity>
   <named-entity nite:id="TS3005c.D.ne.40">
      <nite:pointer role="type"  href="ne-types.xml#id(ne_70)"/>
      <nite:child href="TS3005c.D.words.xml#id(TS3005c.D.words597)"/>
   </named-entity>
   <named-entity nite:id="TS3005c.D.ne.41">
      <nite:pointer role="type"  href="ne-types.xml#id(ne_70)"/>
      <nite:child href="TS3005c.D.words.xml#id(TS3005c.D.words697)"/>
   </named-entity>
   <named-entity nite:id="TS3005c.D.ne.42">
      <nite:pointer role="type"  href="ne-types.xml#id(ne_70)"/>
      <nite:child href="TS3005c.D.words.xml#id(TS3005c.D.words699)"/>
   </named-entity>
   <named-entity nite:id="TS3005c.D.ne.43">
      <nite:pointer role="type"  href="ne-types.xml#id(ne_70)"/>
      <nite:child href="TS3005c.D.words.xml#id(TS3005c.D.words722)"/>
   </named-entity>
   <named-entity nite:id="TS3005c.D.ne.44">
      <nite:pointer role="type"  href="ne-types.xml#id(ne_70)"/>
      <nite:child href="TS3005c.D.words.xml#id(TS3005c.D.words736)"/>
   </named-entity>
   <named-entity nite:id="TS3005c.D.ne.45">
      <nite:pointer role="type"  href="ne-types.xml#id(ne_70)"/>
      <nite:child href="TS3005c.D.words.xml#id(TS3005c.D.words740)"/>
   </named-entity>
   <named-entity nite:id="TS3005c.D.ne.46">
      <nite:pointer role="type"  href="ne-types.xml#id(ne_70)"/>
      <nite:child href="TS3005c.D.words.xml#id(TS3005c.D.words751)"/>
   </named-entity>
   <named-entity nite:id="TS3005c.D.ne.47">
      <nite:pointer role="type"  href="ne-types.xml#id(ne_113)"/>
      <nite:child href="TS3005c.D.words.xml#id(TS3005c.D.words841)..id(TS3005c.D.words842)"/>
   </named-entity>
   <named-entity nite:id="TS3005c.D.ne.48">
      <nite:pointer role="type"  href="ne-types.xml#id(ne_47)"/>
      <nite:child href="TS3005c.D.words.xml#id(TS3005c.D.words867)"/>
   </named-entity>
   <named-entity nite:id="TS3005c.D.ne.49">
      <nite:pointer role="type"  href="ne-types.xml#id(ne_34)"/>
      <nite:child href="TS3005c.D.words.xml#id(TS3005c.D.words873)..id(TS3005c.D.words874)"/>
   </named-entity>
   <named-entity nite:id="TS3005c.D.ne.50">
      <nite:pointer role="type"  href="ne-types.xml#id(ne_47)"/>
      <nite:child href="TS3005c.D.words.xml#id(TS3005c.D.words890)"/>
   </named-entity>
   <named-entity nite:id="TS3005c.D.ne.51">
      <nite:pointer role="type"  href="ne-types.xml#id(ne_34)"/>
      <nite:child href="TS3005c.D.words.xml#id(TS3005c.D.words935)"/>
   </named-entity>
   <named-entity nite:id="TS3005c.D.ne.52">
      <nite:pointer role="type"  href="ne-types.xml#id(ne_34)"/>
      <nite:child href="TS3005c.D.words.xml#id(TS3005c.D.words936)"/>
   </named-entity>
   <named-entity nite:id="TS3005c.D.ne.53">
      <nite:pointer role="type"  href="ne-types.xml#id(ne_34)"/>
      <nite:child href="TS3005c.D.words.xml#id(TS3005c.D.words937)"/>
   </named-entity>
   <named-entity nite:id="TS3005c.D.ne.54">
      <nite:pointer role="type"  href="ne-types.xml#id(ne_34)"/>
      <nite:child href="TS3005c.D.words.xml#id(TS3005c.D.words938)"/>
   </named-entity>
   <named-entity nite:id="TS3005c.D.ne.55">
      <nite:pointer role="type"  href="ne-types.xml#id(ne_34)"/>
      <nite:child href="TS3005c.D.words.xml#id(TS3005c.D.words939)"/>
   </named-entity>
   <named-entity nite:id="TS3005c.D.ne.56">
      <nite:pointer role="type"  href="ne-types.xml#id(ne_34)"/>
      <nite:child href="TS3005c.D.words.xml#id(TS3005c.D.words940)"/>
   </named-entity>
   <named-entity nite:id="TS3005c.D.ne.57">
      <nite:pointer role="type"  href="ne-types.xml#id(ne_34)"/>
      <nite:child href="TS3005c.D.words.xml#id(TS3005c.D.words941)"/>
   </named-entity>
   <named-entity nite:id="TS3005c.D.ne.58">
      <nite:pointer role="type"  href="ne-types.xml#id(ne_47)"/>
      <nite:child href="TS3005c.D.words.xml#id(TS3005c.D.words945)"/>
   </named-entity>
   <named-entity nite:id="TS3005c.D.ne.59">
      <nite:pointer role="type"  href="ne-types.xml#id(ne_34)"/>
      <nite:child href="TS3005c.D.words.xml#id(TS3005c.D.words947)"/>
   </named-entity>
   <named-entity nite:id="TS3005c.D.ne.60">
      <nite:pointer role="type"  href="ne-types.xml#id(ne_34)"/>
      <nite:child href="TS3005c.D.words.xml#id(TS3005c.D.words949)"/>
   </named-entity>
   <named-entity nite:id="TS3005c.D.ne.61">
      <nite:pointer role="type"  href="ne-types.xml#id(ne_34)"/>
      <nite:child href="TS3005c.D.words.xml#id(TS3005c.D.words952)"/>
   </named-entity>
   <named-entity nite:id="TS3005c.D.ne.62">
      <nite:pointer role="type"  href="ne-types.xml#id(ne_34)"/>
      <nite:child href="TS3005c.D.words.xml#id(TS3005c.D.words973)"/>
   </named-entity>
   <named-entity nite:id="TS3005c.D.ne.63">
      <nite:pointer role="type"  href="ne-types.xml#id(ne_47)"/>
      <nite:child href="TS3005c.D.words.xml#id(TS3005c.D.words974)"/>
   </named-entity>
   <named-entity nite:id="TS3005c.D.ne.64">
      <nite:pointer role="type"  href="ne-types.xml#id(ne_47)"/>
      <nite:child href="TS3005c.D.words.xml#id(TS3005c.D.words1169)"/>
   </named-entity>
   <named-entity nite:id="TS3005c.D.ne.65">
      <nite:pointer role="type"  href="ne-types.xml#id(ne_47)"/>
      <nite:child href="TS3005c.D.words.xml#id(TS3005c.D.words1219)"/>
   </named-entity>
   <named-entity nite:id="TS3005c.D.ne.66">
      <nite:pointer role="type"  href="ne-types.xml#id(ne_47)"/>
      <nite:child href="TS3005c.D.words.xml#id(TS3005c.D.words1228)"/>
   </named-entity>
   <named-entity nite:id="TS3005c.D.ne.67">
      <nite:pointer role="type"  href="ne-types.xml#id(ne_60)"/>
      <nite:child href="TS3005c.D.words.xml#id(TS3005c.D.words1263)"/>
   </named-entity>
   <named-entity nite:id="TS3005c.D.ne.68">
      <nite:pointer role="type"  href="ne-types.xml#id(ne_60)"/>
      <nite:child href="TS3005c.D.words.xml#id(TS3005c.D.words1266)"/>
   </named-entity>
   <named-entity nite:id="TS3005c.D.ne.69">
      <nite:pointer role="type"  href="ne-types.xml#id(ne_60)"/>
      <nite:child href="TS3005c.D.words.xml#id(TS3005c.D.words1271)"/>
   </named-entity>
   <named-entity nite:id="TS3005c.D.ne.70">
      <nite:pointer role="type"  href="ne-types.xml#id(ne_60)"/>
      <nite:child href="TS3005c.D.words.xml#id(TS3005c.D.words1283)"/>
   </named-entity>
   <named-entity nite:id="TS3005c.D.ne.71">
      <nite:pointer role="type"  href="ne-types.xml#id(ne_60)"/>
      <nite:child href="TS3005c.D.words.xml#id(TS3005c.D.words1285)"/>
   </named-entity>
   <named-entity nite:id="TS3005c.D.ne.72">
      <nite:pointer role="type"  href="ne-types.xml#id(ne_32)"/>
      <nite:child href="TS3005c.D.words.xml#id(TS3005c.D.words1314)..id(TS3005c.D.words1315)"/>
   </named-entity>
   <named-entity nite:id="TS3005c.D.ne.73">
      <nite:pointer role="type"  href="ne-types.xml#id(ne_47)"/>
      <nite:child href="TS3005c.D.words.xml#id(TS3005c.D.words1349)"/>
   </named-entity>
   <named-entity nite:id="TS3005c.D.ne.74">
      <nite:pointer role="type"  href="ne-types.xml#id(ne_42)"/>
      <nite:child href="TS3005c.D.words.xml#id(TS3005c.D.words1398)"/>
   </named-entity>
   <named-entity nite:id="TS3005c.D.ne.75">
      <nite:pointer role="type"  href="ne-types.xml#id(ne_47)"/>
      <nite:child href="TS3005c.D.words.xml#id(TS3005c.D.words1439)"/>
   </named-entity>
   <named-entity nite:id="TS3005c.D.ne.76">
      <nite:pointer role="type"  href="ne-types.xml#id(ne_47)"/>
      <nite:child href="TS3005c.D.words.xml#id(TS3005c.D.words1478)"/>
   </named-entity>
   <named-entity nite:id="TS3005c.D.ne.77">
      <nite:pointer role="type"  href="ne-types.xml#id(ne_47)"/>
      <nite:child href="TS3005c.D.words.xml#id(TS3005c.D.words1480)"/>
   </named-entity>
   <named-entity nite:id="TS3005c.D.ne.78">
      <nite:pointer role="type"  href="ne-types.xml#id(ne_47)"/>
      <nite:child href="TS3005c.D.words.xml#id(TS3005c.D.words1483)"/>
   </named-entity>
   <named-entity nite:id="TS3005c.D.ne.79">
      <nite:pointer role="type"  href="ne-types.xml#id(ne_47)"/>
      <nite:child href="TS3005c.D.words.xml#id(TS3005c.D.words1488)"/>
   </named-entity>
   <named-entity nite:id="TS3005c.D.ne.80">
      <nite:pointer role="type"  href="ne-types.xml#id(ne_47)"/>
      <nite:child href="TS3005c.D.words.xml#id(TS3005c.D.words1491)"/>
   </named-entity>
   <named-entity nite:id="TS3005c.D.ne.81">
      <nite:pointer role="type"  href="ne-types.xml#id(ne_47)"/>
      <nite:child href="TS3005c.D.words.xml#id(TS3005c.D.words1501)"/>
   </named-entity>
   <named-entity nite:id="TS3005c.D.ne.82">
      <nite:pointer role="type"  href="ne-types.xml#id(ne_47)"/>
      <nite:child href="TS3005c.D.words.xml#id(TS3005c.D.words1510)"/>
   </named-entity>
   <named-entity nite:id="TS3005c.D.ne.83">
      <nite:pointer role="type"  href="ne-types.xml#id(ne_47)"/>
      <nite:child href="TS3005c.D.words.xml#id(TS3005c.D.words1519)"/>
   </named-entity>
   <named-entity nite:id="TS3005c.D.ne.84">
      <nite:pointer role="type"  href="ne-types.xml#id(ne_47)"/>
      <nite:child href="TS3005c.D.words.xml#id(TS3005c.D.words1525)"/>
   </named-entity>
   <named-entity nite:id="TS3005c.D.ne.85">
      <nite:pointer role="type"  href="ne-types.xml#id(ne_47)"/>
      <nite:child href="TS3005c.D.words.xml#id(TS3005c.D.words1535)"/>
   </named-entity>
   <named-entity nite:id="TS3005c.D.ne.86">
      <nite:pointer role="type"  href="ne-types.xml#id(ne_47)"/>
      <nite:child href="TS3005c.D.words.xml#id(TS3005c.D.words1536)"/>
   </named-entity>
   <named-entity nite:id="TS3005c.D.ne.87">
      <nite:pointer role="type"  href="ne-types.xml#id(ne_47)"/>
      <nite:child href="TS3005c.D.words.xml#id(TS3005c.D.words1537)"/>
   </named-entity>
   <named-entity nite:id="TS3005c.D.ne.88">
      <nite:pointer role="type"  href="ne-types.xml#id(ne_47)"/>
      <nite:child href="TS3005c.D.words.xml#id(TS3005c.D.words1540)"/>
   </named-entity>
   <named-entity nite:id="TS3005c.D.ne.89">
      <nite:pointer role="type"  href="ne-types.xml#id(ne_34)"/>
      <nite:child href="TS3005c.D.words.xml#id(TS3005c.D.words1555)"/>
   </named-entity>
   <named-entity nite:id="TS3005c.D.ne.90">
      <nite:pointer role="type"  href="ne-types.xml#id(ne_32)"/>
      <nite:child href="TS3005c.D.words.xml#id(TS3005c.D.words1591)..id(TS3005c.D.words1597)"/>
   </named-entity>
   <named-entity nite:id="TS3005c.D.ne.91">
      <nite:pointer role="type"  href="ne-types.xml#id(ne_32)"/>
      <nite:child href="TS3005c.D.words.xml#id(TS3005c.D.words1601)..id(TS3005c.D.words1604)"/>
   </named-entity>
   <named-entity nite:id="TS3005c.D.ne.92">
      <nite:pointer role="type"  href="ne-types.xml#id(ne_34)"/>
      <nite:child href="TS3005c.D.words.xml#id(TS3005c.D.words1623)"/>
   </named-entity>
   <named-entity nite:id="TS3005c.D.ne.93">
      <nite:pointer role="type"  href="ne-types.xml#id(ne_34)"/>
      <nite:child href="TS3005c.D.words.xml#id(TS3005c.D.words1628)"/>
   </named-entity>
   <named-entity nite:id="TS3005c.D.ne.94">
      <nite:pointer role="type"  href="ne-types.xml#id(ne_34)"/>
      <nite:child href="TS3005c.D.words.xml#id(TS3005c.D.words1632)"/>
   </named-entity>
   <named-entity nite:id="TS3005c.D.ne.95">
      <nite:pointer role="type"  href="ne-types.xml#id(ne_60)"/>
      <nite:child href="TS3005c.D.words.xml#id(TS3005c.D.words1714)"/>
   </named-entity>
   <named-entity nite:id="TS3005c.D.ne.96">
      <nite:pointer role="type"  href="ne-types.xml#id(ne_47)"/>
      <nite:child href="TS3005c.D.words.xml#id(TS3005c.D.words1717)"/>
   </named-entity>
   <named-entity nite:id="TS3005c.D.ne.97">
      <nite:pointer role="type"  href="ne-types.xml#id(ne_47)"/>
      <nite:child href="TS3005c.D.words.xml#id(TS3005c.D.words1774)"/>
   </named-entity>
   <named-entity nite:id="TS3005c.D.ne.98">
      <nite:pointer role="type"  href="ne-types.xml#id(ne_47)"/>
      <nite:child href="TS3005c.D.words.xml#id(TS3005c.D.words1779)"/>
   </named-entity>
   <named-entity nite:id="TS3005c.D.ne.99">
      <nite:pointer role="type"  href="ne-types.xml#id(ne_47)"/>
      <nite:child href="TS3005c.D.words.xml#id(TS3005c.D.words1799)"/>
   </named-entity>
   <named-entity nite:id="TS3005c.D.ne.100">
      <nite:pointer role="type"  href="ne-types.xml#id(ne_47)"/>
      <nite:child href="TS3005c.D.words.xml#id(TS3005c.D.words1811)"/>
   </named-entity>
   <named-entity nite:id="TS3005c.D.ne.101">
      <nite:pointer role="type"  href="ne-types.xml#id(ne_47)"/>
      <nite:child href="TS3005c.D.words.xml#id(TS3005c.D.words1853)"/>
   </named-entity>
   <named-entity nite:id="TS3005c.D.ne.102">
      <nite:pointer role="type"  href="ne-types.xml#id(ne_50)"/>
      <nite:child href="TS3005c.D.words.xml#id(TS3005c.D.words1935)"/>
   </named-entity>
   <named-entity nite:id="TS3005c.D.ne.103">
      <nite:pointer role="type"  href="ne-types.xml#id(ne_50)"/>
      <nite:child href="TS3005c.D.words.xml#id(TS3005c.D.words1961)"/>
   </named-entity>
   <named-entity nite:id="TS3005c.D.ne.104">
      <nite:pointer role="type"  href="ne-types.xml#id(ne_50)"/>
      <nite:child href="TS3005c.D.words.xml#id(TS3005c.D.words1969)"/>
   </named-entity>
   <named-entity nite:id="TS3005c.D.ne.105">
      <nite:pointer role="type"  href="ne-types.xml#id(ne_50)"/>
      <nite:child href="TS3005c.D.words.xml#id(TS3005c.D.words1977)"/>
   </named-entity>
   <named-entity nite:id="TS3005c.D.ne.106">
      <nite:pointer role="type"  href="ne-types.xml#id(ne_50)"/>
      <nite:child href="TS3005c.D.words.xml#id(TS3005c.D.words1979)"/>
   </named-entity>
   <named-entity nite:id="TS3005c.D.ne.107">
      <nite:pointer role="type"  href="ne-types.xml#id(ne_50)"/>
      <nite:child href="TS3005c.D.words.xml#id(TS3005c.D.words1984)"/>
   </named-entity>
   <named-entity nite:id="TS3005c.D.ne.108">
      <nite:pointer role="type"  href="ne-types.xml#id(ne_50)"/>
      <nite:child href="TS3005c.D.words.xml#id(TS3005c.D.words1985)"/>
   </named-entity>
   <named-entity nite:id="TS3005c.D.ne.109">
      <nite:pointer role="type"  href="ne-types.xml#id(ne_50)"/>
      <nite:child href="TS3005c.D.words.xml#id(TS3005c.D.words1997)"/>
   </named-entity>
   <named-entity nite:id="TS3005c.D.ne.110">
      <nite:pointer role="type"  href="ne-types.xml#id(ne_50)"/>
      <nite:child href="TS3005c.D.words.xml#id(TS3005c.D.words1999)"/>
   </named-entity>
   <named-entity nite:id="TS3005c.D.ne.111">
      <nite:pointer role="type"  href="ne-types.xml#id(ne_34)"/>
      <nite:child href="TS3005c.D.words.xml#id(TS3005c.D.words2009)"/>
   </named-entity>
   <named-entity nite:id="TS3005c.D.ne.112">
      <nite:pointer role="type"  href="ne-types.xml#id(ne_50)"/>
      <nite:child href="TS3005c.D.words.xml#id(TS3005c.D.words2022)..id(TS3005c.D.words2023)"/>
   </named-entity>
   <named-entity nite:id="TS3005c.D.ne.113">
      <nite:pointer role="type"  href="ne-types.xml#id(ne_50)"/>
      <nite:child href="TS3005c.D.words.xml#id(TS3005c.D.words2029)"/>
   </named-entity>
   <named-entity nite:id="TS3005c.D.ne.114">
      <nite:pointer role="type"  href="ne-types.xml#id(ne_50)"/>
      <nite:child href="TS3005c.D.words.xml#id(TS3005c.D.words2031)"/>
   </named-entity>
   <named-entity nite:id="TS3005c.D.ne.115">
      <nite:pointer role="type"  href="ne-types.xml#id(ne_70)"/>
      <nite:child href="TS3005c.D.words.xml#id(TS3005c.D.words2033)"/>
   </named-entity>
   <named-entity nite:id="TS3005c.D.ne.116">
      <nite:pointer role="type"  href="ne-types.xml#id(ne_50)"/>
      <nite:child href="TS3005c.D.words.xml#id(TS3005c.D.words2035)"/>
   </named-entity>
   <named-entity nite:id="TS3005c.D.ne.117">
      <nite:pointer role="type"  href="ne-types.xml#id(ne_50)"/>
      <nite:child href="TS3005c.D.words.xml#id(TS3005c.D.words2052)"/>
   </named-entity>
   <named-entity nite:id="TS3005c.D.ne.118">
      <nite:pointer role="type"  href="ne-types.xml#id(ne_22)"/>
      <nite:child href="TS3005c.D.words.xml#id(TS3005c.D.words2056)"/>
   </named-entity>
   <named-entity nite:id="TS3005c.D.ne.119">
      <nite:pointer role="type"  href="ne-types.xml#id(ne_50)"/>
      <nite:child href="TS3005c.D.words.xml#id(TS3005c.D.words2060)"/>
   </named-entity>
   <named-entity nite:id="TS3005c.D.ne.120">
      <nite:pointer role="type"  href="ne-types.xml#id(ne_50)"/>
      <nite:child href="TS3005c.D.words.xml#id(TS3005c.D.words2062)"/>
   </named-entity>
   <named-entity nite:id="TS3005c.D.ne.121">
      <nite:pointer role="type"  href="ne-types.xml#id(ne_50)"/>
      <nite:child href="TS3005c.D.words.xml#id(TS3005c.D.words2065)..id(TS3005c.D.words2066)"/>
   </named-entity>
   <named-entity nite:id="TS3005c.D.ne.122">
      <nite:pointer role="type"  href="ne-types.xml#id(ne_50)"/>
      <nite:child href="TS3005c.D.words.xml#id(TS3005c.D.words2068)"/>
   </named-entity>
</nite:root>